gene_cluster_matrix/__init__.py
gene_cluster_matrix/__main__.py
gene_cluster_matrix/core.py
gene_cluster_matrix/gff_parse.py
gene_cluster_matrix/make_plotly_data.py
gene_cluster_matrix/make_plotly_fig.py
gene_cluster_matrix/make_tree.py
gene_cluster_matrix/parse_args.py
gene_cluster_matrix-0.1.4.dist-info/LICENSE
gene_cluster_matrix-0.1.4.dist-info/METADATA
gene_cluster_matrix-0.1.4.dist-info/WHEEL
gene_cluster_matrix-0.1.4.dist-info/entry_points.txt
gene_cluster_matrix-0.1.4.dist-info/top_level.txt
gene_cluster_matrix-0.1.4.dist-info/RECORD
