Metadata-Version: 2.1
Name: gene-cluster-matrix
Version: 0.1.4
Summary: Visualization library for gene cluster & distance
Home-page: https://github.com/slt666666/gene_cluster_matrix
Author: Toshiyuki Sakai
Author-email: toshi6661024@gmail.com
Maintainer: Toshiyuki Sakai
Maintainer-email: toshi6661024@gmail.com
License: MIT
Platform: UNKNOWN
Requires-Python: >=3.6
Requires-Dist: numpy
Requires-Dist: pandas
Requires-Dist: plotly
Requires-Dist: gffutils
Requires-Dist: toytree
Requires-Dist: Pillow
